<Source>
  <Function name="init">
    <Source>
      <InstructionCall>
        <FunctionCall name="connect">
          <CallArguments>
            <Value>
              <Member>
                <Identifier name="this"/>
                <FunctionCall name="cursor"/>
              </Member>
            </Value>
            <Value>
              <Constant delim="&quot;" type="String" value="cursorUpdated()"/>
            </Value>
            <Value>
              <Identifier name="this"/>
            </Value>
            <Value>
              <Constant delim="&quot;" type="String" value="actualizarAreas"/>
            </Value>
          </CallArguments>
        </FunctionCall>
      </InstructionCall>
    </Source>
  </Function>
  <Function name="actualizarAreas">
    <Source>
      <InstructionCall>
        <Member>
          <Identifier name="sys"/>
          <FunctionCall name="updateAreas"/>
        </Member>
      </InstructionCall>
    </Source>
  </Function>
</Source>
